{
  "permissions": [
    {
      "id": "user.create",
      "name": "Create User",
      "description": "Allows creation of new user accounts",
      "module": "User Management"
    },
    {
      "id": "user.read",
      "name": "View Users",
      "description": "Allows viewing of user lists and details",
      "module": "User Management"
    },
    {
      "id": "user.update",
      "name": "Update User",
      "description": "Allows modification of user details and roles",
      "module": "User Management"
    },
    {
      "id": "user.delete",
      "name": "Delete User",
      "description": "Allows deletion of existing users",
      "module": "User Management"
    },
    {
      "id": "user.activate",
      "name": "Activate/Deactivate User",
      "description": "Allows toggling user activation status",
      "module": "User Management"
    },
    {
      "id": "user.export",
      "name": "Export Users",
      "description": "Allows exporting user data in various formats",
      "module": "User Management"
    },
    {
      "id": "role.create",
      "name": "Create Role",
      "description": "Allows creation of new roles",
      "module": "Role Management"
    },
    {
      "id": "role.read",
      "name": "View Roles",
      "description": "Allows viewing of role lists and details",
      "module": "Role Management"
    },
    {
      "id": "role.update",
      "name": "Update Role",
      "description": "Allows modification of role details and permissions",
      "module": "Role Management"
    },
    {
      "id": "role.delete",
      "name": "Delete Role",
      "description": "Allows deletion of existing roles",
      "module": "Role Management"
    },
    {
      "id": "role.export",
      "name": "Export Roles",
      "description": "Allows exporting role data in various formats",
      "module": "Role Management"
    },
    {
      "id": "permission.read",
      "name": "View Permissions",
      "description": "Allows viewing of permission lists",
      "module": "Permission Management"
    },
    {
      "id": "permission.assign",
      "name": "Assign Permissions",
      "description": "Allows assigning permissions to roles or users",
      "module": "Permission Management"
    },
    {
      "id": "report.generate",
      "name": "Generate Reports",
      "description": "Allows generation of system reports",
      "module": "Reporting"
    },
    {
      "id": "report.view",
      "name": "View Reports",
      "description": "Allows viewing of generated reports",
      "module": "Reporting"
    },
    {
      "id": "report.download",
      "name": "Download Reports",
      "description": "Allows downloading of system-generated reports",
      "module": "Reporting"
    },
    {
      "id": "report.export",
      "name": "Export Reports",
      "description": "Allows exporting reports in various formats",
      "module": "Reporting"
    },
    {
      "id": "dashboard.view",
      "name": "View Dashboard",
      "description": "Allows access to system dashboard",
      "module": "Dashboard"
    },
    {
      "id": "dashboard.admin",
      "name": "Admin Dashboard",
      "description": "Allows access to administrative dashboard features",
      "module": "Dashboard"
    },
    {
      "id": "contract.create",
      "name": "Create Contract",
      "description": "Allows creation of new contracts",
      "module": "Contract Management"
    },
    {
      "id": "contract.read",
      "name": "View Contracts",
      "description": "Allows viewing of contract lists and details",
      "module": "Contract Management"
    },
    {
      "id": "contract.update",
      "name": "Update Contract",
      "description": "Allows modification of contract details",
      "module": "Contract Management"
    },
    {
      "id": "contract.delete",
      "name": "Delete Contract",
      "description": "Allows deletion of existing contracts",
      "module": "Contract Management"
    },
    {
      "id": "contract.approve",
      "name": "Approve Contract",
      "description": "Allows approval of contracts",
      "module": "Contract Management"
    },
    {
      "id": "contract.export",
      "name": "Export Contracts",
      "description": "Allows exporting contract data",
      "module": "Contract Management"
    },
    {
      "id": "notification.send",
      "name": "Send Notifications",
      "description": "Allows sending system notifications",
      "module": "Communication"
    },
    {
      "id": "notification.view",
      "name": "View Notifications",
      "description": "Allows viewing notification history",
      "module": "Communication"
    },
    {
      "id": "audit.view",
      "name": "View Audit Logs",
      "description": "Allows viewing system audit logs",
      "module": "System Administration"
    },
    {
      "id": "system.backup",
      "name": "System Backup",
      "description": "Allows performing system backups",
      "module": "System Administration"
    },
    {
      "id": "system.restore",
      "name": "System Restore",
      "description": "Allows restoring system from backups",
      "module": "System Administration"
    },
    {
      "id": "system.config",
      "name": "System Configuration",
      "description": "Allows modification of system configurations",
      "module": "System Administration"
    },
    {
      "id": "analytics.view",
      "name": "View Analytics",
      "description": "Allows viewing system analytics",
      "module": "Analytics"
    },
    {
      "id": "analytics.export",
      "name": "Export Analytics",
      "description": "Allows exporting analytics data",
      "module": "Analytics"
    },
    {
      "id": "finance.view",
      "name": "View Financial Data",
      "description": "Allows viewing financial information",
      "module": "Finance"
    },
    {
      "id": "finance.manage",
      "name": "Manage Finance",
      "description": "Allows managing financial transactions",
      "module": "Finance"
    },
    {
      "id": "finance.export",
      "name": "Export Financial Data",
      "description": "Allows exporting financial reports",
      "module": "Finance"
    },
    {
      "id": "inventory.view",
      "name": "View Inventory",
      "description": "Allows viewing inventory items",
      "module": "Inventory Management"
    },
    {
      "id": "inventory.manage",
      "name": "Manage Inventory",
      "description": "Allows managing inventory items",
      "module": "Inventory Management"
    },
    {
      "id": "inventory.export",
      "name": "Export Inventory",
      "description": "Allows exporting inventory data",
      "module": "Inventory Management"
    },
    {
      "id": "support.view",
      "name": "View Support Tickets",
      "description": "Allows viewing customer support tickets",
      "module": "Customer Support"
    },
    {
      "id": "support.manage",
      "name": "Manage Support Tickets",
      "description": "Allows managing customer support tickets",
      "module": "Customer Support"
    },
    {
      "id": "integration.configure",
      "name": "Configure Integrations",
      "description": "Allows configuring external integrations",
      "module": "Integration Management"
    },
    {
      "id": "integration.monitor",
      "name": "Monitor Integrations",
      "description": "Allows monitoring integration status",
      "module": "Integration Management"
    },
    {
      "id": "api.access",
      "name": "API Access",
      "description": "Allows access to system APIs",
      "module": "API Management"
    },
    {
      "id": "api.manage",
      "name": "Manage API Keys",
      "description": "Allows managing API keys and access",
      "module": "API Management"
    },
    {
      "id": "security.view",
      "name": "View Security Logs",
      "description": "Allows viewing security and access logs",
      "module": "Security"
    },
    {
      "id": "security.manage",
      "name": "Manage Security Settings",
      "description": "Allows managing security configurations",
      "module": "Security"
    },
    {
      "id": "email.send",
      "name": "Send Emails",
      "description": "Allows sending system emails",
      "module": "Communication"
    },
    {
      "id": "template.manage",
      "name": "Manage Templates",
      "description": "Allows managing email and document templates",
      "module": "Template Management"
    },
    {
      "id": "workflow.view",
      "name": "View Workflows",
      "description": "Allows viewing system workflows",
      "module": "Workflow Management"
    },
    {
      "id": "workflow.manage",
      "name": "Manage Workflows",
      "description": "Allows creating and managing workflows",
      "module": "Workflow Management"
    },
    {
      "id": "settings.read",
      "name": "View Settings",
      "description": "Allows viewing of system settings",
      "module": "Settings Management"
    },
    {
      "id": "settings.create",
      "name": "Create Settings",
      "description": "Allows creation of new setting fields",
      "module": "Settings Management"
    },
    {
      "id": "settings.update",
      "name": "Update Settings",
      "description": "Allows modification of existing settings",
      "module": "Settings Management"
    },
    {
      "id": "settings.delete",
      "name": "Delete Settings",
      "description": "Allows deletion of setting fields",
      "module": "Settings Management"
    }
  ]
}